Workbook

Sheet Instrucciones
A1: Presupuesto Detallado y APU (5D) - Plantilla
A3: Objetivo: base de datos de Análisis de Precios Unitarios (APU) y presupuesto por capítulos y rubros, con códigos WBS y CBS (RA2).
A5: Flujo de trabajo
A6: 1. 'Parametros': defina AIU e IVA. Los porcentajes que trae son supuestos de ejemplo: ajústelos y cite la fuente que use.
A7: 2. 'Insumos': liste materiales, mano de obra, equipo y transporte con su precio unitario y fuente (CAMACOL, SICMA, INVIAS, cotización).
A8: 3. 'APU': una fila por insumo de cada APU (Cód APU + Cód insumo + cantidad por unidad de APU). Descripción, tipo, unidad y precio se traen solos.
A9: 4. 'APU_Resumen': escriba los códigos de APU; se calculan materiales, mano de obra, equipo, transporte y total directo.
A10: 5. 'Presupuesto': por ítem, WBS, código OmniClass, código CBS, cantidad (copiada de la hoja Resumen del QTO) y Cód APU. Valor unitario y total se calculan.
A11: 6. 'Resumen': costo directo por capítulo, AIU, IVA sobre utilidad y total. Ese total es el BAC para la Curva S.
A13: AVISO: los precios de los ejemplos (concreto, bomba, cuadrillas, ladrillo) provienen de las tarifas del archivo Casa Candelaria del usuario; son solo ilustrativos. Reemplácelos con su banco de precios.
A15: Texto azul sobre fondo amarillo = celda que usted debe llenar
A16: Texto negro = fórmula (no la sobrescriba)
A17: Fondo verde = fila de EJEMPLO con datos ilustrativos: bórrela o reemplácela con sus datos

Sheet Parametros
A1: Parámetros
A2: Supuestos editables - documente la fuente de cada uno
A3: Parámetro | B3: Valor | C3: Nota / fuente
A4: Administración (% costo directo) | B4: 0.15 | C4: Supuesto de ejemplo - confirmar con el docente o la fuente
A5: Imprevistos (% costo directo) | B5: 0.05 | C5: Supuesto de ejemplo
A6: Utilidad (% costo directo) | B6: 0.05 | C6: Supuesto de ejemplo
A7: IVA sobre utilidad | B7: 0.19 | C7: Tarifa general de IVA en Colombia - verificar vigencia
A8: Moneda | B8: COP
A9: Fecha de precios | C9: Fecha de la fuente de precios

Sheet Insumos
A1: Insumos y precios unitarios
A2: Hasta 100 insumos
A5: Código | B5: Descripción | C5: Tipo | D5: Unidad | E5: Precio unitario | F5: Fuente | G5: Fecha
A6: I-001 | B6: Concreto premezclado 3000 PSI | C6: MATERIAL | D6: m³ | E6: 450000 | F6: EJEMPLO - tarifa del .mpp del usuario
A7: I-002 | B7: Ladrillo pastillero | C7: MATERIAL | D7: mill | E7: 1800000 | F7: EJEMPLO - tarifa del .mpp del usuario
A8: I-003 | B8: Cuadrilla obra civil | C8: MANO DE OBRA | D8: h | E8: 15000 | F8: EJEMPLO - tarifa del .mpp del usuario
A9: I-004 | B9: Ayudante general | C9: MANO DE OBRA | D9: h | E9: 12000 | F9: EJEMPLO - tarifa del .mpp del usuario
A10: I-005 | B10: Bomba estacionaria | C10: EQUIPO | D10: h | E10: 95000 | F10: EJEMPLO - tarifa del .mpp del usuario

Sheet APU
A1: Análisis de Precios Unitarios (detalle por insumo)
A2: Una fila por insumo de cada APU. Hasta 300 filas
A5: Cód APU | B5: Descripción APU | C5: Unidad APU | D5: Cód insumo | E5: Descripción insumo | F5: Tipo | G5: Unid. | H5: Cantidad por unidad de APU | I5: Precio unitario | J5: Parcial | L5: Cantidades del ejemplo (desperdicio 5 %, rendimiento de cuadrilla) son supuestos ilustrativos.
A6: A-2.2 | B6: Fundición de vigas de cimentación (concreto 3000 PSI) | C6: m³ | D6: I-001 | E6: =IF(D6="","",IFERROR(INDEX(Insumos!$B$6:$B$105,MATCH(D6,Insumos!$A$6:$A$105,0)),"No existe")) -> Concreto premezclado 3000 PSI | F6: =IF(D6="","",IFERROR(INDEX(Insumos!$C$6:$C$105,MATCH(D6,Insumos!$A$6:$A$105,0)),"")) -> MATERIAL | G6: =IF(D6="","",IFERROR(INDEX(Insumos!$D$6:$D$105,MATCH(D6,Insumos!$A$6:$A$105,0)),"")) -> m³ | H6: 1.05 | I6: =IF(D6="","",IFERROR(INDEX(Insumos!$E$6:$E$105,MATCH(D6,Insumos!$A$6:$A$105,0)),0)) -> 450000 | J6: =IF(OR(D6="",H6=""),"",H6*I6) -> 472500
A7: A-2.2 | B7: Fundición de vigas de cimentación (concreto 3000 PSI) | C7: m³ | D7: I-003 | E7: =IF(D7="","",IFERROR(INDEX(Insumos!$B$6:$B$105,MATCH(D7,Insumos!$A$6:$A$105,0)),"No existe")) -> Cuadrilla obra civil | F7: =IF(D7="","",IFERROR(INDEX(Insumos!$C$6:$C$105,MATCH(D7,Insumos!$A$6:$A$105,0)),"")) -> MANO DE OBRA | G7: =IF(D7="","",IFERROR(INDEX(Insumos!$D$6:$D$105,MATCH(D7,Insumos!$A$6:$A$105,0)),"")) -> h | H7: 3 | I7: =IF(D7="","",IFERROR(INDEX(Insumos!$E$6:$E$105,MATCH(D7,Insumos!$A$6:$A$105,0)),0)) -> 15000 | J7: =IF(OR(D7="",H7=""),"",H7*I7) -> 45000
A8: A-2.2 | B8: Fundición de vigas de cimentación (concreto 3000 PSI) | C8: m³ | D8: I-004 | E8: =IF(D8="","",IFERROR(INDEX(Insumos!$B$6:$B$105,MATCH(D8,Insumos!$A$6:$A$105,0)),"No existe")) -> Ayudante general | F8: =IF(D8="","",IFERROR(INDEX(Insumos!$C$6:$C$105,MATCH(D8,Insumos!$A$6:$A$105,0)),"")) -> MANO DE OBRA | G8: =IF(D8="","",IFERROR(INDEX(Insumos!$D$6:$D$105,MATCH(D8,Insumos!$A$6:$A$105,0)),"")) -> h | H8: 3 | I8: =IF(D8="","",IFERROR(INDEX(Insumos!$E$6:$E$105,MATCH(D8,Insumos!$A$6:$A$105,0)),0)) -> 12000 | J8: =IF(OR(D8="",H8=""),"",H8*I8) -> 36000
A9: A-2.2 | B9: Fundición de vigas de cimentación (concreto 3000 PSI) | C9: m³ | D9: I-005 | E9: =IF(D9="","",IFERROR(INDEX(Insumos!$B$6:$B$105,MATCH(D9,Insumos!$A$6:$A$105,0)),"No existe")) -> Bomba estacionaria | F9: =IF(D9="","",IFERROR(INDEX(Insumos!$C$6:$C$105,MATCH(D9,Insumos!$A$6:$A$105,0)),"")) -> EQUIPO | G9: =IF(D9="","",IFERROR(INDEX(Insumos!$D$6:$D$105,MATCH(D9,Insumos!$A$6:$A$105,0)),"")) -> h | H9: 0.25 | I9: =IF(D9="","",IFERROR(INDEX(Insumos!$E$6:$E$105,MATCH(D9,Insumos!$A$6:$A$105,0)),0)) -> 95000 | J9: =IF(OR(D9="",H9=""),"",H9*I9) -> 23750
E10: =IF(D10="","",IFERROR(INDEX(Insumos!$B$6:$B$105,MATCH(D10,Insumos!$A$6:$A$105,0)),"No existe")) | F10: =IF(D10="","",IFERROR(INDEX(Insumos!$C$6:$C$105,MATCH(D10,Insumos!$A$6:$A$105,0)),"")) | G10: =IF(D10="","",IFERROR(INDEX(Insumos!$D$6:$D$105,MATCH(D10,Insumos!$A$6:$A$105,0)),"")) | I10: =IF(D10="","",IFERROR(INDEX(Insumos!$E$6:$E$105,MATCH(D10,Insumos!$A$6:$A$105,0)),0)) | J10: =IF(OR(D10="",H10=""),"",H10*I10)
E11: =IF(D11="","",IFERROR(INDEX(Insumos!$B$6:$B$105,MATCH(D11,Insumos!$A$6:$A$105,0)),"No existe")) | F11: =IF(D11="","",IFERROR(INDEX(Insumos!$C$6:$C$105,MATCH(D11,Insumos!$A$6:$A$105,0)),"")) | G11: =IF(D11="","",IFERROR(INDEX(Insumos!$D$6:$D$105,MATCH(D11,Insumos!$A$6:$A$105,0)),"")) | I11: =IF(D11="","",IFERROR(INDEX(Insumos!$E$6:$E$105,MATCH(D11,Insumos!$A$6:$A$105,0)),0)) | J11: =IF(OR(D11="",H11=""),"",H11*I11)
E12: =IF(D12="","",IFERROR(INDEX(Insumos!$B$6:$B$105,MATCH(D12,Insumos!$A$6:$A$105,0)),"No existe")) | F12: =IF(D12="","",IFERROR(INDEX(Insumos!$C$6:$C$105,MATCH(D12,Insumos!$A$6:$A$105,0)),"")) | G12: =IF(D12="","",IFERROR(INDEX(Insumos!$D$6:$D$105,MATCH(D12,Insumos!$A$6:$A$105,0)),"")) | I12: =IF(D12="","",IFERROR(INDEX(Insumos!$E$6:$E$105,MATCH(D12,Insumos!$A$6:$A$105,0)),0)) | J12: =IF(OR(D12="",H12=""),"",H12*I12)
E13: =IF(D13="","",IFERROR(INDEX(Insumos!$B$6:$B$105,MATCH(D13,Insumos!$A$6:$A$105,0)),"No existe")) | F13: =IF(D13="","",IFERROR(INDEX(Insumos!$C$6:$C$105,MATCH(D13,Insumos!$A$6:$A$105,0)),"")) | G13: =IF(D13="","",IFERROR(INDEX(Insumos!$D$6:$D$105,MATCH(D13,Insumos!$A$6:$A$105,0)),"")) | I13: =IF(D13="","",IFERROR(INDEX(Insumos!$E$6:$E$105,MATCH(D13,Insumos!$A$6:$A$105,0)),0)) | J13: =IF(OR(D13="",H13=""),"",H13*I13)
E14: =IF(D14="","",IFERROR(INDEX(Insumos!$B$6:$B$105,MATCH(D14,Insumos!$A$6:$A$105,0)),"No existe")) | F14: =IF(D14="","",IFERROR(INDEX(Insumos!$C$6:$C$105,MATCH(D14,Insumos!$A$6:$A$105,0)),"")) | G14: =IF(D14="","",IFERROR(INDEX(Insumos!$D$6:$D$105,MATCH(D14,Insumos!$A$6:$A$105,0)),"")) | I14: =IF(D14="","",IFERROR(INDEX(Insumos!$E$6:$E$105,MATCH(D14,Insumos!$A$6:$A$105,0)),0)) | J14: =IF(OR(D14="",H14=""),"",H14*I14)
E15: =IF(D15="","",IFERROR(INDEX(Insumos!$B$6:$B$105,MATCH(D15,Insumos!$A$6:$A$105,0)),"No existe")) | F15: =IF(D15="","",IFERROR(INDEX(Insumos!$C$6:$C$105,MATCH(D15,Insumos!$A$6:$A$105,0)),"")) | G15: =IF(D15="","",IFERROR(INDEX(Insumos!$D$6:$D$105,MATCH(D15,Insumos!$A$6:$A$105,0)),"")) | I15: =IF(D15="","",IFERROR(INDEX(Insumos!$E$6:$E$105,MATCH(D15,Insumos!$A$6:$A$105,0)),0)) | J15: =IF(OR(D15="",H15=""),"",H15*I15)
E16: =IF(D16="","",IFERROR(INDEX(Insumos!$B$6:$B$105,MATCH(D16,Insumos!$A$6:$A$105,0)),"No existe")) | F16: =IF(D16="","",IFERROR(INDEX(Insumos!$C$6:$C$105,MATCH(D16,Insumos!$A$6:$A$105,0)),"")) | G16: =IF(D16="","",IFERROR(INDEX(Insumos!$D$6:$D$105,MATCH(D16,Insumos!$A$6:$A$105,0)),"")) | I16: =IF(D16="","",IFERROR(INDEX(Insumos!$E$6:$E$105,MATCH(D16,Insumos!$A$6:$A$105,0)),0)) | J16: =IF(OR(D16="",H16=""),"",H16*I16)
E17: =IF(D17="","",IFERROR(INDEX(Insumos!$B$6:$B$105,MATCH(D17,Insumos!$A$6:$A$105,0)),"No existe")) | F17: =IF(D17="","",IFERROR(INDEX(Insumos!$C$6:$C$105,MATCH(D17,Insumos!$A$6:$A$105,0)),"")) | G17: =IF(D17="","",IFERROR(INDEX(Insumos!$D$6:$D$105,MATCH(D17,Insumos!$A$6:$A$105,0)),"")) | I17: =IF(D17="","",IFERROR(INDEX(Insumos!$E$6:$E$105,MATCH(D17,Insumos!$A$6:$A$105,0)),0)) | J17: =IF(OR(D17="",H17=""),"",H17*I17)
E18: =IF(D18="","",IFERROR(INDEX(Insumos!$B$6:$B$105,MATCH(D18,Insumos!$A$6:$A$105,0)),"No existe")) | F18: =IF(D18="","",IFERROR(INDEX(Insumos!$C$6:$C$105,MATCH(D18,Insumos!$A$6:$A$105,0)),"")) | G18: =IF(D18="","",IFERROR(INDEX(Insumos!$D$6:$D$105,MATCH(D18,Insumos!$A$6:$A$105,0)),"")) | I18: =IF(D18="","",IFERROR(INDEX(Insumos!$E$6:$E$105,MATCH(D18,Insumos!$A$6:$A$105,0)),0)) | J18: =IF(OR(D18="",H18=""),"",H18*I18)
E19: =IF(D19="","",IFERROR(INDEX(Insumos!$B$6:$B$105,MATCH(D19,Insumos!$A$6:$A$105,0)),"No existe")) | F19: =IF(D19="","",IFERROR(INDEX(Insumos!$C$6:$C$105,MATCH(D19,Insumos!$A$6:$A$105,0)),"")) | G19: =IF(D19="","",IFERROR(INDEX(Insumos!$D$6:$D$105,MATCH(D19,Insumos!$A$6:$A$105,0)),"")) | I19: =IF(D19="","",IFERROR(INDEX(Insumos!$E$6:$E$105,MATCH(D19,Insumos!$A$6:$A$105,0)),0)) | J19: =IF(OR(D19="",H19=""),"",H19*I19)
E20: =IF(D20="","",IFERROR(INDEX(Insumos!$B$6:$B$105,MATCH(D20,Insumos!$A$6:$A$105,0)),"No existe")) | F20: =IF(D20="","",IFERROR(INDEX(Insumos!$C$6:$C$105,MATCH(D20,Insumos!$A$6:$A$105,0)),"")) | G20: =IF(D20="","",IFERROR(INDEX(Insumos!$D$6:$D$105,MATCH(D20,Insumos!$A$6:$A$105,0)),"")) | I20: =IF(D20="","",IFERROR(INDEX(Insumos!$E$6:$E$105,MATCH(D20,Insumos!$A$6:$A$105,0)),0)) | J20: =IF(OR(D20="",H20=""),"",H20*I20)
E21: =IF(D21="","",IFERROR(INDEX(Insumos!$B$6:$B$105,MATCH(D21,Insumos!$A$6:$A$105,0)),"No existe")) | F21: =IF(D21="","",IFERROR(INDEX(Insumos!$C$6:$C$105,MATCH(D21,Insumos!$A$6:$A$105,0)),"")) | G21: =IF(D21="","",IFERROR(INDEX(Insumos!$D$6:$D$105,MATCH(D21,Insumos!$A$6:$A$105,0)),"")) | I21: =IF(D21="","",IFERROR(INDEX(Insumos!$E$6:$E$105,MATCH(D21,Insumos!$A$6:$A$105,0)),0)) | J21: =IF(OR(D21="",H21=""),"",H21*I21)
... E305: =IF(D305="","",IFERROR(INDEX(Insumos!$B$6:$B$105,MATCH(D305,Insumos!$A$6:$A$105,0)),"No existe")) | F305: =IF(D305="","",IFERROR(INDEX(Insumos!$C$6:$C$105,MATCH(D305,Insumos!$A$6:$A$105,0)),"")) | G305: =IF(D305="","",IFERROR(INDEX(Insumos!$D$6:$D$105,MATCH(D305,Insumos!$A$6:$A$105,0)),"")) | I305: =IF(D305="","",IFERROR(INDEX(Insumos!$E$6:$E$105,MATCH(D305,Insumos!$A$6:$A$105,0)),0)) | J305: =IF(OR(D305="",H305=""),"",H305*I305)

Sheet APU_Resumen
A1: Resumen de APU
A2: Escriba los códigos de APU (columna A); el resto se calcula
A5: Cód APU | B5: Descripción | C5: Unidad | D5: Materiales | E5: Mano de obra | F5: Equipo | G5: Transporte | H5: Total directo unitario
A6: A-2.2 | B6: =IF(A6="","",IFERROR(INDEX(APU!$B$6:$B$305,MATCH(A6,APU!$A$6:$A$305,0)),"No existe")) -> Fundición de vigas de cimentación (concreto 3000 PSI) | C6: =IF(A6="","",IFERROR(INDEX(APU!$C$6:$C$305,MATCH(A6,APU!$A$6:$A$305,0)),"")) -> m³ | D6: =IF($A6="","",SUMIFS(APU!$J$6:$J$305,APU!$A$6:$A$305,$A6,APU!$F$6:$F$305,"MATERIAL")) -> 472500 | E6: =IF($A6="","",SUMIFS(APU!$J$6:$J$305,APU!$A$6:$A$305,$A6,APU!$F$6:$F$305,"MANO DE OBRA")) -> 81000 | F6: =IF($A6="","",SUMIFS(APU!$J$6:$J$305,APU!$A$6:$A$305,$A6,APU!$F$6:$F$305,"EQUIPO")) -> 23750 | G6: =IF($A6="","",SUMIFS(APU!$J$6:$J$305,APU!$A$6:$A$305,$A6,APU!$F$6:$F$305,"TRANSPORTE")) -> 0 | H6: =IF(A6="","",SUM(D6:G6)) -> 577250
B7: =IF(A7="","",IFERROR(INDEX(APU!$B$6:$B$305,MATCH(A7,APU!$A$6:$A$305,0)),"No existe")) | C7: =IF(A7="","",IFERROR(INDEX(APU!$C$6:$C$305,MATCH(A7,APU!$A$6:$A$305,0)),"")) | D7: =IF($A7="","",SUMIFS(APU!$J$6:$J$305,APU!$A$6:$A$305,$A7,APU!$F$6:$F$305,"MATERIAL")) | E7: =IF($A7="","",SUMIFS(APU!$J$6:$J$305,APU!$A$6:$A$305,$A7,APU!$F$6:$F$305,"MANO DE OBRA")) | F7: =IF($A7="","",SUMIFS(APU!$J$6:$J$305,APU!$A$6:$A$305,$A7,APU!$F$6:$F$305,"EQUIPO")) | G7: =IF($A7="","",SUMIFS(APU!$J$6:$J$305,APU!$A$6:$A$305,$A7,APU!$F$6:$F$305,"TRANSPORTE")) | H7: =IF(A7="","",SUM(D7:G7))
B8: =IF(A8="","",IFERROR(INDEX(APU!$B$6:$B$305,MATCH(A8,APU!$A$6:$A$305,0)),"No existe")) | C8: =IF(A8="","",IFERROR(INDEX(APU!$C$6:$C$305,MATCH(A8,APU!$A$6:$A$305,0)),"")) | D8: =IF($A8="","",SUMIFS(APU!$J$6:$J$305,APU!$A$6:$A$305,$A8,APU!$F$6:$F$305,"MATERIAL")) | E8: =IF($A8="","",SUMIFS(APU!$J$6:$J$305,APU!$A$6:$A$305,$A8,APU!$F$6:$F$305,"MANO DE OBRA")) | F8: =IF($A8="","",SUMIFS(APU!$J$6:$J$305,APU!$A$6:$A$305,$A8,APU!$F$6:$F$305,"EQUIPO")) | G8: =IF($A8="","",SUMIFS(APU!$J$6:$J$305,APU!$A$6:$A$305,$A8,APU!$F$6:$F$305,"TRANSPORTE")) | H8: =IF(A8="","",SUM(D8:G8))
B9: =IF(A9="","",IFERROR(INDEX(APU!$B$6:$B$305,MATCH(A9,APU!$A$6:$A$305,0)),"No existe")) | C9: =IF(A9="","",IFERROR(INDEX(APU!$C$6:$C$305,MATCH(A9,APU!$A$6:$A$305,0)),"")) | D9: =IF($A9="","",SUMIFS(APU!$J$6:$J$305,APU!$A$6:$A$305,$A9,APU!$F$6:$F$305,"MATERIAL")) | E9: =IF($A9="","",SUMIFS(APU!$J$6:$J$305,APU!$A$6:$A$305,$A9,APU!$F$6:$F$305,"MANO DE OBRA")) | F9: =IF($A9="","",SUMIFS(APU!$J$6:$J$305,APU!$A$6:$A$305,$A9,APU!$F$6:$F$305,"EQUIPO")) | G9: =IF($A9="","",SUMIFS(APU!$J$6:$J$305,APU!$A$6:$A$305,$A9,APU!$F$6:$F$305,"TRANSPORTE")) | H9: =IF(A9="","",SUM(D9:G9))
B10: =IF(A10="","",IFERROR(INDEX(APU!$B$6:$B$305,MATCH(A10,APU!$A$6:$A$305,0)),"No existe")) | C10: =IF(A10="","",IFERROR(INDEX(APU!$C$6:$C$305,MATCH(A10,APU!$A$6:$A$305,0)),"")) | D10: =IF($A10="","",SUMIFS(APU!$J$6:$J$305,APU!$A$6:$A$305,$A10,APU!$F$6:$F$305,"MATERIAL")) | E10: =IF($A10="","",SUMIFS(APU!$J$6:$J$305,APU!$A$6:$A$305,$A10,APU!$F$6:$F$305,"MANO DE OBRA")) | F10: =IF($A10="","",SUMIFS(APU!$J$6:$J$305,APU!$A$6:$A$305,$A10,APU!$F$6:$F$305,"EQUIPO")) | G10: =IF($A10="","",SUMIFS(APU!$J$6:$J$305,APU!$A$6:$A$305,$A10,APU!$F$6:$F$305,"TRANSPORTE")) | H10: =IF(A10="","",SUM(D10:G10))
B11: =IF(A11="","",IFERROR(INDEX(APU!$B$6:$B$305,MATCH(A11,APU!$A$6:$A$305,0)),"No existe")) | C11: =IF(A11="","",IFERROR(INDEX(APU!$C$6:$C$305,MATCH(A11,APU!$A$6:$A$305,0)),"")) | D11: =IF($A11="","",SUMIFS(APU!$J$6:$J$305,APU!$A$6:$A$305,$A11,APU!$F$6:$F$305,"MATERIAL")) | E11: =IF($A11="","",SUMIFS(APU!$J$6:$J$305,APU!$A$6:$A$305,$A11,APU!$F$6:$F$305,"MANO DE OBRA")) | F11: =IF($A11="","",SUMIFS(APU!$J$6:$J$305,APU!$A$6:$A$305,$A11,APU!$F$6:$F$305,"EQUIPO")) | G11: =IF($A11="","",SUMIFS(APU!$J$6:$J$305,APU!$A$6:$A$305,$A11,APU!$F$6:$F$305,"TRANSPORTE")) | H11: =IF(A11="","",SUM(D11:G11))
B12: =IF(A12="","",IFERROR(INDEX(APU!$B$6:$B$305,MATCH(A12,APU!$A$6:$A$305,0)),"No existe")) | C12: =IF(A12="","",IFERROR(INDEX(APU!$C$6:$C$305,MATCH(A12,APU!$A$6:$A$305,0)),"")) | D12: =IF($A12="","",SUMIFS(APU!$J$6:$J$305,APU!$A$6:$A$305,$A12,APU!$F$6:$F$305,"MATERIAL")) | E12: =IF($A12="","",SUMIFS(APU!$J$6:$J$305,APU!$A$6:$A$305,$A12,APU!$F$6:$F$305,"MANO DE OBRA")) | F12: =IF($A12="","",SUMIFS(APU!$J$6:$J$305,APU!$A$6:$A$305,$A12,APU!$F$6:$F$305,"EQUIPO")) | G12: =IF($A12="","",SUMIFS(APU!$J$6:$J$305,APU!$A$6:$A$305,$A12,APU!$F$6:$F$305,"TRANSPORTE")) | H12: =IF(A12="","",SUM(D12:G12))
B13: =IF(A13="","",IFERROR(INDEX(APU!$B$6:$B$305,MATCH(A13,APU!$A$6:$A$305,0)),"No existe")) | C13: =IF(A13="","",IFERROR(INDEX(APU!$C$6:$C$305,MATCH(A13,APU!$A$6:$A$305,0)),"")) | D13: =IF($A13="","",SUMIFS(APU!$J$6:$J$305,APU!$A$6:$A$305,$A13,APU!$F$6:$F$305,"MATERIAL")) | E13: =IF($A13="","",SUMIFS(APU!$J$6:$J$305,APU!$A$6:$A$305,$A13,APU!$F$6:$F$305,"MANO DE OBRA")) | F13: =IF($A13="","",SUMIFS(APU!$J$6:$J$305,APU!$A$6:$A$305,$A13,APU!$F$6:$F$305,"EQUIPO")) | G13: =IF($A13="","",SUMIFS(APU!$J$6:$J$305,APU!$A$6:$A$305,$A13,APU!$F$6:$F$305,"TRANSPORTE")) | H13: =IF(A13="","",SUM(D13:G13))
B14: =IF(A14="","",IFERROR(INDEX(APU!$B$6:$B$305,MATCH(A14,APU!$A$6:$A$305,0)),"No existe")) | C14: =IF(A14="","",IFERROR(INDEX(APU!$C$6:$C$305,MATCH(A14,APU!$A$6:$A$305,0)),"")) | D14: =IF($A14="","",SUMIFS(APU!$J$6:$J$305,APU!$A$6:$A$305,$A14,APU!$F$6:$F$305,"MATERIAL")) | E14: =IF($A14="","",SUMIFS(APU!$J$6:$J$305,APU!$A$6:$A$305,$A14,APU!$F$6:$F$305,"MANO DE OBRA")) | F14: =IF($A14="","",SUMIFS(APU!$J$6:$J$305,APU!$A$6:$A$305,$A14,APU!$F$6:$F$305,"EQUIPO")) | G14: =IF($A14="","",SUMIFS(APU!$J$6:$J$305,APU!$A$6:$A$305,$A14,APU!$F$6:$F$305,"TRANSPORTE")) | H14: =IF(A14="","",SUM(D14:G14))
B15: =IF(A15="","",IFERROR(INDEX(APU!$B$6:$B$305,MATCH(A15,APU!$A$6:$A$305,0)),"No existe")) | C15: =IF(A15="","",IFERROR(INDEX(APU!$C$6:$C$305,MATCH(A15,APU!$A$6:$A$305,0)),"")) | D15: =IF($A15="","",SUMIFS(APU!$J$6:$J$305,APU!$A$6:$A$305,$A15,APU!$F$6:$F$305,"MATERIAL")) | E15: =IF($A15="","",SUMIFS(APU!$J$6:$J$305,APU!$A$6:$A$305,$A15,APU!$F$6:$F$305,"MANO DE OBRA")) | F15: =IF($A15="","",SUMIFS(APU!$J$6:$J$305,APU!$A$6:$A$305,$A15,APU!$F$6:$F$305,"EQUIPO")) | G15: =IF($A15="","",SUMIFS(APU!$J$6:$J$305,APU!$A$6:$A$305,$A15,APU!$F$6:$F$305,"TRANSPORTE")) | H15: =IF(A15="","",SUM(D15:G15))
B16: =IF(A16="","",IFERROR(INDEX(APU!$B$6:$B$305,MATCH(A16,APU!$A$6:$A$305,0)),"No existe")) | C16: =IF(A16="","",IFERROR(INDEX(APU!$C$6:$C$305,MATCH(A16,APU!$A$6:$A$305,0)),"")) | D16: =IF($A16="","",SUMIFS(APU!$J$6:$J$305,APU!$A$6:$A$305,$A16,APU!$F$6:$F$305,"MATERIAL")) | E16: =IF($A16="","",SUMIFS(APU!$J$6:$J$305,APU!$A$6:$A$305,$A16,APU!$F$6:$F$305,"MANO DE OBRA")) | F16: =IF($A16="","",SUMIFS(APU!$J$6:$J$305,APU!$A$6:$A$305,$A16,APU!$F$6:$F$305,"EQUIPO")) | G16: =IF($A16="","",SUMIFS(APU!$J$6:$J$305,APU!$A$6:$A$305,$A16,APU!$F$6:$F$305,"TRANSPORTE")) | H16: =IF(A16="","",SUM(D16:G16))
B17: =IF(A17="","",IFERROR(INDEX(APU!$B$6:$B$305,MATCH(A17,APU!$A$6:$A$305,0)),"No existe")) | C17: =IF(A17="","",IFERROR(INDEX(APU!$C$6:$C$305,MATCH(A17,APU!$A$6:$A$305,0)),"")) | D17: =IF($A17="","",SUMIFS(APU!$J$6:$J$305,APU!$A$6:$A$305,$A17,APU!$F$6:$F$305,"MATERIAL")) | E17: =IF($A17="","",SUMIFS(APU!$J$6:$J$305,APU!$A$6:$A$305,$A17,APU!$F$6:$F$305,"MANO DE OBRA")) | F17: =IF($A17="","",SUMIFS(APU!$J$6:$J$305,APU!$A$6:$A$305,$A17,APU!$F$6:$F$305,"EQUIPO")) | G17: =IF($A17="","",SUMIFS(APU!$J$6:$J$305,APU!$A$6:$A$305,$A17,APU!$F$6:$F$305,"TRANSPORTE")) | H17: =IF(A17="","",SUM(D17:G17))
B18: =IF(A18="","",IFERROR(INDEX(APU!$B$6:$B$305,MATCH(A18,APU!$A$6:$A$305,0)),"No existe")) | C18: =IF(A18="","",IFERROR(INDEX(APU!$C$6:$C$305,MATCH(A18,APU!$A$6:$A$305,0)),"")) | D18: =IF($A18="","",SUMIFS(APU!$J$6:$J$305,APU!$A$6:$A$305,$A18,APU!$F$6:$F$305,"MATERIAL")) | E18: =IF($A18="","",SUMIFS(APU!$J$6:$J$305,APU!$A$6:$A$305,$A18,APU!$F$6:$F$305,"MANO DE OBRA")) | F18: =IF($A18="","",SUMIFS(APU!$J$6:$J$305,APU!$A$6:$A$305,$A18,APU!$F$6:$F$305,"EQUIPO")) | G18: =IF($A18="","",SUMIFS(APU!$J$6:$J$305,APU!$A$6:$A$305,$A18,APU!$F$6:$F$305,"TRANSPORTE")) | H18: =IF(A18="","",SUM(D18:G18))
... B65: =IF(A65="","",IFERROR(INDEX(APU!$B$6:$B$305,MATCH(A65,APU!$A$6:$A$305,0)),"No existe")) | C65: =IF(A65="","",IFERROR(INDEX(APU!$C$6:$C$305,MATCH(A65,APU!$A$6:$A$305,0)),"")) | D65: =IF($A65="","",SUMIFS(APU!$J$6:$J$305,APU!$A$6:$A$305,$A65,APU!$F$6:$F$305,"MATERIAL")) | E65: =IF($A65="","",SUMIFS(APU!$J$6:$J$305,APU!$A$6:$A$305,$A65,APU!$F$6:$F$305,"MANO DE OBRA")) | F65: =IF($A65="","",SUMIFS(APU!$J$6:$J$305,APU!$A$6:$A$305,$A65,APU!$F$6:$F$305,"EQUIPO")) | G65: =IF($A65="","",SUMIFS(APU!$J$6:$J$305,APU!$A$6:$A$305,$A65,APU!$F$6:$F$305,"TRANSPORTE")) | H65: =IF(A65="","",SUM(D65:G65))

Sheet Presupuesto
A1: Presupuesto detallado
A2: Cantidades: copiar desde QTO > Resumen. Hasta 200 ítems
I3: Costo directo total: | J3: =SUM(J6:J205) -> 7157900
A5: Ítem (WBS) | B5: Capítulo | C5: Código OmniClass | D5: Código CBS | E5: Descripción | F5: Unidad | G5: Cantidad | H5: Cód APU | I5: Valor unitario | J5: Valor total | K5: % del directo
A6: 2.2 | B6: 2 Cimentación y estructura | C6: 21-02 10 10 20 | D6: C-02.02 | E6: Fundición de vigas de cimentación | F6: =IF(H6="","",IFERROR(INDEX(APU_Resumen!$C$6:$C$65,MATCH(H6,APU_Resumen!$A$6:$A$65,0)),"")) -> m³ | G6: 12.4 | H6: A-2.2 | I6: =IF(H6="","",IFERROR(INDEX(APU_Resumen!$H$6:$H$65,MATCH(H6,APU_Resumen!$A$6:$A$65,0)),"Sin APU")) -> 577250 | J6: =IF(OR(G6="",NOT(ISNUMBER(I6))),"",G6*I6) -> 7157900 | K6: =IF(OR(J6="",$J$3=0),"",J6/$J$3) -> 1
F7: =IF(H7="","",IFERROR(INDEX(APU_Resumen!$C$6:$C$65,MATCH(H7,APU_Resumen!$A$6:$A$65,0)),"")) | I7: =IF(H7="","",IFERROR(INDEX(APU_Resumen!$H$6:$H$65,MATCH(H7,APU_Resumen!$A$6:$A$65,0)),"Sin APU")) | J7: =IF(OR(G7="",NOT(ISNUMBER(I7))),"",G7*I7) | K7: =IF(OR(J7="",$J$3=0),"",J7/$J$3)
F8: =IF(H8="","",IFERROR(INDEX(APU_Resumen!$C$6:$C$65,MATCH(H8,APU_Resumen!$A$6:$A$65,0)),"")) | I8: =IF(H8="","",IFERROR(INDEX(APU_Resumen!$H$6:$H$65,MATCH(H8,APU_Resumen!$A$6:$A$65,0)),"Sin APU")) | J8: =IF(OR(G8="",NOT(ISNUMBER(I8))),"",G8*I8) | K8: =IF(OR(J8="",$J$3=0),"",J8/$J$3)
F9: =IF(H9="","",IFERROR(INDEX(APU_Resumen!$C$6:$C$65,MATCH(H9,APU_Resumen!$A$6:$A$65,0)),"")) | I9: =IF(H9="","",IFERROR(INDEX(APU_Resumen!$H$6:$H$65,MATCH(H9,APU_Resumen!$A$6:$A$65,0)),"Sin APU")) | J9: =IF(OR(G9="",NOT(ISNUMBER(I9))),"",G9*I9) | K9: =IF(OR(J9="",$J$3=0),"",J9/$J$3)
F10: =IF(H10="","",IFERROR(INDEX(APU_Resumen!$C$6:$C$65,MATCH(H10,APU_Resumen!$A$6:$A$65,0)),"")) | I10: =IF(H10="","",IFERROR(INDEX(APU_Resumen!$H$6:$H$65,MATCH(H10,APU_Resumen!$A$6:$A$65,0)),"Sin APU")) | J10: =IF(OR(G10="",NOT(ISNUMBER(I10))),"",G10*I10) | K10: =IF(OR(J10="",$J$3=0),"",J10/$J$3)
F11: =IF(H11="","",IFERROR(INDEX(APU_Resumen!$C$6:$C$65,MATCH(H11,APU_Resumen!$A$6:$A$65,0)),"")) | I11: =IF(H11="","",IFERROR(INDEX(APU_Resumen!$H$6:$H$65,MATCH(H11,APU_Resumen!$A$6:$A$65,0)),"Sin APU")) | J11: =IF(OR(G11="",NOT(ISNUMBER(I11))),"",G11*I11) | K11: =IF(OR(J11="",$J$3=0),"",J11/$J$3)
F12: =IF(H12="","",IFERROR(INDEX(APU_Resumen!$C$6:$C$65,MATCH(H12,APU_Resumen!$A$6:$A$65,0)),"")) | I12: =IF(H12="","",IFERROR(INDEX(APU_Resumen!$H$6:$H$65,MATCH(H12,APU_Resumen!$A$6:$A$65,0)),"Sin APU")) | J12: =IF(OR(G12="",NOT(ISNUMBER(I12))),"",G12*I12) | K12: =IF(OR(J12="",$J$3=0),"",J12/$J$3)
F13: =IF(H13="","",IFERROR(INDEX(APU_Resumen!$C$6:$C$65,MATCH(H13,APU_Resumen!$A$6:$A$65,0)),"")) | I13: =IF(H13="","",IFERROR(INDEX(APU_Resumen!$H$6:$H$65,MATCH(H13,APU_Resumen!$A$6:$A$65,0)),"Sin APU")) | J13: =IF(OR(G13="",NOT(ISNUMBER(I13))),"",G13*I13) | K13: =IF(OR(J13="",$J$3=0),"",J13/$J$3)
F14: =IF(H14="","",IFERROR(INDEX(APU_Resumen!$C$6:$C$65,MATCH(H14,APU_Resumen!$A$6:$A$65,0)),"")) | I14: =IF(H14="","",IFERROR(INDEX(APU_Resumen!$H$6:$H$65,MATCH(H14,APU_Resumen!$A$6:$A$65,0)),"Sin APU")) | J14: =IF(OR(G14="",NOT(ISNUMBER(I14))),"",G14*I14) | K14: =IF(OR(J14="",$J$3=0),"",J14/$J$3)
F15: =IF(H15="","",IFERROR(INDEX(APU_Resumen!$C$6:$C$65,MATCH(H15,APU_Resumen!$A$6:$A$65,0)),"")) | I15: =IF(H15="","",IFERROR(INDEX(APU_Resumen!$H$6:$H$65,MATCH(H15,APU_Resumen!$A$6:$A$65,0)),"Sin APU")) | J15: =IF(OR(G15="",NOT(ISNUMBER(I15))),"",G15*I15) | K15: =IF(OR(J15="",$J$3=0),"",J15/$J$3)
F16: =IF(H16="","",IFERROR(INDEX(APU_Resumen!$C$6:$C$65,MATCH(H16,APU_Resumen!$A$6:$A$65,0)),"")) | I16: =IF(H16="","",IFERROR(INDEX(APU_Resumen!$H$6:$H$65,MATCH(H16,APU_Resumen!$A$6:$A$65,0)),"Sin APU")) | J16: =IF(OR(G16="",NOT(ISNUMBER(I16))),"",G16*I16) | K16: =IF(OR(J16="",$J$3=0),"",J16/$J$3)
F17: =IF(H17="","",IFERROR(INDEX(APU_Resumen!$C$6:$C$65,MATCH(H17,APU_Resumen!$A$6:$A$65,0)),"")) | I17: =IF(H17="","",IFERROR(INDEX(APU_Resumen!$H$6:$H$65,MATCH(H17,APU_Resumen!$A$6:$A$65,0)),"Sin APU")) | J17: =IF(OR(G17="",NOT(ISNUMBER(I17))),"",G17*I17) | K17: =IF(OR(J17="",$J$3=0),"",J17/$J$3)
F18: =IF(H18="","",IFERROR(INDEX(APU_Resumen!$C$6:$C$65,MATCH(H18,APU_Resumen!$A$6:$A$65,0)),"")) | I18: =IF(H18="","",IFERROR(INDEX(APU_Resumen!$H$6:$H$65,MATCH(H18,APU_Resumen!$A$6:$A$65,0)),"Sin APU")) | J18: =IF(OR(G18="",NOT(ISNUMBER(I18))),"",G18*I18) | K18: =IF(OR(J18="",$J$3=0),"",J18/$J$3)
... F205: =IF(H205="","",IFERROR(INDEX(APU_Resumen!$C$6:$C$65,MATCH(H205,APU_Resumen!$A$6:$A$65,0)),"")) | I205: =IF(H205="","",IFERROR(INDEX(APU_Resumen!$H$6:$H$65,MATCH(H205,APU_Resumen!$A$6:$A$65,0)),"Sin APU")) | J205: =IF(OR(G205="",NOT(ISNUMBER(I205))),"",G205*I205) | K205: =IF(OR(J205="",$J$3=0),"",J205/$J$3)

Sheet Resumen
A1: Resumen del presupuesto
A2: El total es el BAC (línea base de costo) para la Curva S
A4: Capítulo | B4: Costo directo
A5: 1 Obras preliminares | B5: =IF(A5="","",SUMIFS(Presupuesto!$J$6:$J$205,Presupuesto!$B$6:$B$205,A5)) -> 0
A6: 2 Cimentación y estructura | B6: =IF(A6="","",SUMIFS(Presupuesto!$J$6:$J$205,Presupuesto!$B$6:$B$205,A6)) -> 7157900
A7: 3 Acabados | B7: =IF(A7="","",SUMIFS(Presupuesto!$J$6:$J$205,Presupuesto!$B$6:$B$205,A7)) -> 0
A8: 4 Carpintería y metálica | B8: =IF(A8="","",SUMIFS(Presupuesto!$J$6:$J$205,Presupuesto!$B$6:$B$205,A8)) -> 0
A9: 5 Cubierta | B9: =IF(A9="","",SUMIFS(Presupuesto!$J$6:$J$205,Presupuesto!$B$6:$B$205,A9)) -> 0
A10: 6 Pintura y limpieza | B10: =IF(A10="","",SUMIFS(Presupuesto!$J$6:$J$205,Presupuesto!$B$6:$B$205,A10)) -> 0
B11: =IF(A11="","",SUMIFS(Presupuesto!$J$6:$J$205,Presupuesto!$B$6:$B$205,A11))
B12: =IF(A12="","",SUMIFS(Presupuesto!$J$6:$J$205,Presupuesto!$B$6:$B$205,A12))
B13: =IF(A13="","",SUMIFS(Presupuesto!$J$6:$J$205,Presupuesto!$B$6:$B$205,A13))
B14: =IF(A14="","",SUMIFS(Presupuesto!$J$6:$J$205,Presupuesto!$B$6:$B$205,A14))
A15: Costo directo total | B15: =SUM(B5:B14) -> 7157900
A16: Administración | B16: =B15*Parametros!B4 -> 1073685
A17: Imprevistos | B17: =B15*Parametros!B5 -> 357895
A18: Utilidad | B18: =B15*Parametros!B6 -> 357895
A19: IVA sobre utilidad | B19: =B18*Parametros!B7 -> 68000.05
A20: TOTAL PRESUPUESTO (BAC) | B20: =B15+B16+B17+B18+B19 -> 9015375.1
A21: Control: directo en Presupuesto vs suma por capítulo | B21: =IF(ROUND(Presupuesto!J3-B15,0)=0,"OK","Hay ítems sin capítulo") -> OK
