Workbook

Sheet Instrucciones
A1: Curva S y Análisis EVM - Plantilla
A3: Objetivo: construir la Curva S (costo planificado acumulado) y el análisis de valor ganado (EVM) con desviaciones y escenarios What-If (RA4).
A5: Cómo usarla
A6: 1. 'Parametros': BAC (total del presupuesto), fecha de inicio, plazo en meses y período de corte (el mes hasta el cual hay avance real).
A7: 2. 'Curva_S': en la columna C escriba el costo planificado por mes (de Microsoft Project: Uso de tareas / Resumen de flujo de caja). Hasta 12 períodos.
A8: 3. Cada mes registre el costo real (AC) y el % de avance físico acumulado; copie hacia abajo las fórmulas de las columnas G, I, J, K, L, M de la fila anterior.
A9: 4. 'EVM_Resumen' calcula SV, CV, SPI, CPI, EAC, ETC, VAC y TCPI al período de corte.
A10: 5. 'WhatIf' compara escenarios de rendimiento de costo y de cronograma (editables).
A12: Las fórmulas siguen la guía PMBOK: EV = BAC x % avance; CPI = EV/AC; SPI = EV/PV; EAC (tendencia) = AC + (BAC - EV)/CPI.
A13: AVISO: los valores del ejemplo (BAC de 100 millones, avance de 4 meses) son ILUSTRATIVOS; reemplácelos con los de su proyecto.
A15: Texto azul sobre fondo amarillo = celda que usted debe llenar
A16: Texto negro = fórmula (no la sobrescriba)
A17: Fondo verde = fila de EJEMPLO con datos ilustrativos: bórrela o reemplácela con sus datos

Sheet Parametros
A1: Parámetros
A2: Celdas amarillas = datos del proyecto
A3: Parámetro | B3: Valor | C3: Nota
A4: BAC - Presupuesto total del proyecto ($) | B4: 100000000 | C4: De la hoja Resumen del presupuesto (EJEMPLO ilustrativo)
A5: Fecha de inicio de obra | B5: 46328 | C5: Debe coincidir con el cronograma en Project
A6: Plazo total (meses) | B6: 12 | C6: Máximo 12 en esta plantilla
A7: Período de corte (mes N con avance real) | B7: 4 | C7: Último mes con costo real y avance registrados

Sheet Curva_S
A1: Curva S - Costo planificado, ganado y real
A2: PV: de Project · AC y % avance: seguimiento mensual
A6: Período | B6: Mes | C6: PV período ($) | D6: PV acumulado ($) | E6: % PV acum. | F6: AC período ($) | G6: AC acumulado ($) | H6: % avance físico acum. | I6: EV acumulado ($) | J6: CPI | K6: SPI | L6: CV ($) | M6: SV ($)
A7: 1 | B7: =EDATE(Parametros!$B$5,A7-1) -> 46328 | C7: 3000000 | D7: =SUM($C$7:C7) -> 3000000 | E7: =IF(Parametros!$B$4=0,"",D7/Parametros!$B$4) -> 0.03 | F7: 3200000 | G7: =SUM($F$7:F7) -> 3200000 | H7: 0.03 | I7: =Parametros!$B$4*H7 -> 3000000 | J7: =IF(G7=0,"",I7/G7) -> 0.9375 | K7: =IF(D7=0,"",I7/D7) -> 1 | L7: =I7-G7 -> -200000 | M7: =I7-D7 -> 0
A8: 2 | B8: =EDATE(Parametros!$B$5,A8-1) -> 46358 | C8: 5000000 | D8: =SUM($C$7:C8) -> 8000000 | E8: =IF(Parametros!$B$4=0,"",D8/Parametros!$B$4) -> 0.08 | F8: 5600000 | G8: =SUM($F$7:F8) -> 8800000 | H8: 0.075 | I8: =Parametros!$B$4*H8 -> 7500000 | J8: =IF(G8=0,"",I8/G8) -> 0.85227273 | K8: =IF(D8=0,"",I8/D8) -> 0.9375 | L8: =I8-G8 -> -1300000 | M8: =I8-D8 -> -500000
A9: 3 | B9: =EDATE(Parametros!$B$5,A9-1) -> 46389 | C9: 8000000 | D9: =SUM($C$7:C9) -> 16000000 | E9: =IF(Parametros!$B$4=0,"",D9/Parametros!$B$4) -> 0.16 | F9: 8900000 | G9: =SUM($F$7:F9) -> 17700000 | H9: 0.15 | I9: =Parametros!$B$4*H9 -> 15000000 | J9: =IF(G9=0,"",I9/G9) -> 0.84745763 | K9: =IF(D9=0,"",I9/D9) -> 0.9375 | L9: =I9-G9 -> -2700000 | M9: =I9-D9 -> -1000000
A10: 4 | B10: =EDATE(Parametros!$B$5,A10-1) -> 46420 | C10: 10000000 | D10: =SUM($C$7:C10) -> 26000000 | E10: =IF(Parametros!$B$4=0,"",D10/Parametros!$B$4) -> 0.26 | F10: 10800000 | G10: =SUM($F$7:F10) -> 28500000 | H10: 0.24 | I10: =Parametros!$B$4*H10 -> 24000000 | J10: =IF(G10=0,"",I10/G10) -> 0.84210526 | K10: =IF(D10=0,"",I10/D10) -> 0.92307692 | L10: =I10-G10 -> -4500000 | M10: =I10-D10 -> -2000000
A11: 5 | B11: =EDATE(Parametros!$B$5,A11-1) -> 46448 | C11: 12000000 | D11: =SUM($C$7:C11) -> 38000000 | E11: =IF(Parametros!$B$4=0,"",D11/Parametros!$B$4) -> 0.38
A12: 6 | B12: =EDATE(Parametros!$B$5,A12-1) -> 46479 | C12: 14000000 | D12: =SUM($C$7:C12) -> 52000000 | E12: =IF(Parametros!$B$4=0,"",D12/Parametros!$B$4) -> 0.52
A13: 7 | B13: =EDATE(Parametros!$B$5,A13-1) -> 46509 | C13: 14000000 | D13: =SUM($C$7:C13) -> 66000000 | E13: =IF(Parametros!$B$4=0,"",D13/Parametros!$B$4) -> 0.66
A14: 8 | B14: =EDATE(Parametros!$B$5,A14-1) -> 46540 | C14: 12000000 | D14: =SUM($C$7:C14) -> 78000000 | E14: =IF(Parametros!$B$4=0,"",D14/Parametros!$B$4) -> 0.78
A15: 9 | B15: =EDATE(Parametros!$B$5,A15-1) -> 46570 | C15: 9000000 | D15: =SUM($C$7:C15) -> 87000000 | E15: =IF(Parametros!$B$4=0,"",D15/Parametros!$B$4) -> 0.87
A16: 10 | B16: =EDATE(Parametros!$B$5,A16-1) -> 46601 | C16: 7000000 | D16: =SUM($C$7:C16) -> 94000000 | E16: =IF(Parametros!$B$4=0,"",D16/Parametros!$B$4) -> 0.94
A17: 11 | B17: =EDATE(Parametros!$B$5,A17-1) -> 46632 | C17: 4000000 | D17: =SUM($C$7:C17) -> 98000000 | E17: =IF(Parametros!$B$4=0,"",D17/Parametros!$B$4) -> 0.98
A18: 12 | B18: =EDATE(Parametros!$B$5,A18-1) -> 46662 | C18: 2000000 | D18: =SUM($C$7:C18) -> 100000000 | E18: =IF(Parametros!$B$4=0,"",D18/Parametros!$B$4) -> 1
A20: Filas 5-12 de las columnas G, I, J, K, L, M se dejan vacías a propósito (el gráfico no dibuja períodos sin ejecutar). Copie las fórmulas de la fila anterior al registrar cada mes.
A21: Control: suma PV período vs BAC | D21: =IF(ROUND(SUM(C7:C18)-Parametros!B4,0)=0,"OK","PV no suma el BAC") -> OK

Sheet EVM_Resumen
A1: Indicadores EVM al período de corte
A2: Todo se calcula desde 'Curva_S' y 'Parametros'
A4: Indicador | B4: Valor | C4: Interpretación
A5: BAC - Presupuesto total | B5: =Parametros!B4 -> 100000000
A6: PV - Valor planificado | B6: =INDEX(Curva_S!$D$7:$D$18,Parametros!$B$7) -> 26000000
A7: EV - Valor ganado | B7: =INDEX(Curva_S!$I$7:$I$18,Parametros!$B$7) -> 24000000
A8: AC - Costo real | B8: =INDEX(Curva_S!$G$7:$G$18,Parametros!$B$7) -> 28500000
A9: CV = EV - AC | B9: =B7-B8 -> -4500000 | C9: =IF(B9<0,"Sobrecosto","Bajo presupuesto o en presupuesto") -> Sobrecosto
A10: SV = EV - PV | B10: =B7-B6 -> -2000000 | C10: =IF(B10<0,"Atraso respecto a lo planificado","Adelantado o en cronograma") -> Atraso respecto a lo planificado
A11: CPI = EV / AC | B11: =IF(B8=0,"",B7/B8) -> 0.84210526 | C11: =IF(B11="","",IF(B11<1,"Se gasta más de lo ganado","Eficiencia de costo aceptable")) -> Se gasta más de lo ganado
A12: SPI = EV / PV | B12: =IF(B6=0,"",B7/B6) -> 0.92307692 | C12: =IF(B12="","",IF(B12<1,"Avance menor al planificado","Avance igual o mayor al planificado")) -> Avance menor al planificado
A13: EAC (tendencia) = AC + (BAC - EV)/CPI | B13: =IF(B11="","",B8+(B5-B7)/B11) -> 118750000 | C13: Costo final proyectado si se mantiene el CPI actual
A14: ETC = EAC - AC | B14: =IF(B13="","",B13-B8) -> 90250000 | C14: Costo que falta por gastar
A15: VAC = BAC - EAC | B15: =IF(B13="","",B5-B13) -> -18750000 | C15: =IF(B15="","",IF(B15<0,"Proyección de sobrecosto","Proyección dentro de presupuesto")) -> Proyección de sobrecosto
A16: TCPI = (BAC - EV)/(BAC - AC) | B16: =IF(B5-B8=0,"",(B5-B7)/(B5-B8)) -> 1.0629371 | C16: Eficiencia requerida de aquí en adelante para cerrar en el BAC
A17: Plazo proyectado (meses) = plazo / SPI | B17: =IF(B12="","",Parametros!B6/B12) -> 13 | C17: Estimación simple por SPI actual
A18: % avance real vs % planificado | B18: =IF(B5=0,"",B7/B5) -> 0.24 | C18: ="Planificado a la fecha: "&TEXT(B6/B5,"0.0%") -> Planificado a la fecha: 26.0%

Sheet WhatIf
A1: Escenarios What-If
A2: Edite los factores amarillos (supuestos del usuario)
A4: Escenario | B4: CPI futuro supuesto | C4: SPI futuro supuesto | D4: EAC ($) | E4: VAC = BAC - EAC ($) | F4: Plazo proyectado (meses) | G4: Comentario
A5: Tendencia actual | B5: =EVM_Resumen!B11 -> 0.84210526 | C5: =EVM_Resumen!B12 -> 0.92307692 | D5: =IF(OR(B5="",B5=0),"",EVM_Resumen!$B$8+(EVM_Resumen!$B$5-EVM_Resumen!$B$7)/B5) -> 118750000 | E5: =IF(D5="","",EVM_Resumen!$B$5-D5) -> -18750000 | F5: =IF(OR(C5="",C5=0),"",Parametros!$B$6/C5) -> 13 | G5: Se mantiene el desempeño observado
A6: Optimista (se recupera) | B6: 1 | C6: 1 | D6: =IF(OR(B6="",B6=0),"",EVM_Resumen!$B$8+(EVM_Resumen!$B$5-EVM_Resumen!$B$7)/B6) -> 104500000 | E6: =IF(D6="","",EVM_Resumen!$B$5-D6) -> -4500000 | F6: =IF(OR(C6="",C6=0),"",Parametros!$B$6/C6) -> 12 | G6: Supuesto: se recupera el costo y el cronograma
A7: Pesimista | B7: 0.8 | C7: 0.85 | D7: =IF(OR(B7="",B7=0),"",EVM_Resumen!$B$8+(EVM_Resumen!$B$5-EVM_Resumen!$B$7)/B7) -> 123500000 | E7: =IF(D7="","",EVM_Resumen!$B$5-D7) -> -23500000 | F7: =IF(OR(C7="",C7=0),"",Parametros!$B$6/C7) -> 14.117647 | G7: Supuesto de ejemplo - ajustar
A8: Personalizado | B8: 0.9 | C8: 0.9 | D8: =IF(OR(B8="",B8=0),"",EVM_Resumen!$B$8+(EVM_Resumen!$B$5-EVM_Resumen!$B$7)/B8) -> 1.1294444e+08 | E8: =IF(D8="","",EVM_Resumen!$B$5-D8) -> -12944444 | F8: =IF(OR(C8="",C8=0),"",Parametros!$B$6/C8) -> 13.333333 | G8: Defina su propio escenario
A10: Fila 'Tendencia actual' usa los indicadores reales (negro); las demás filas son supuestos editables (azul).
